example_package_vitorscmoreira/__init__.py
example_package_vitorscmoreira/example.py
example_package_vitorscmoreira-0.0.2.dist-info/METADATA
example_package_vitorscmoreira-0.0.2.dist-info/WHEEL
example_package_vitorscmoreira-0.0.2.dist-info/top_level.txt
example_package_vitorscmoreira-0.0.2.dist-info/RECORD
