Metadata-Version: 2.1
Name: example_package_vitorscmoreira
Version: 0.0.2
Summary: Package description
Author: Vitor Moreira
Author-email: vitorscmoreira@hotmail.com
Keywords: python,rpa
Classifier: Development Status :: 1 - Planning
Classifier: Intended Audience :: Developers
Classifier: Programming Language :: Python :: 3
Classifier: Operating System :: Unix
Classifier: Operating System :: MacOS :: MacOS X
Classifier: Operating System :: Microsoft :: Windows
Requires-Dist: os
